[{
  "_id": {
    "$oid": "5fc47b1d80c84c61f8b3ffa3"
  },
  "link": "/havocOs-ysl",
  "date": {
    "$date": "2020-11-30T04:54:53.093Z"
  },
  "heading": "HavocOs[3.11][OFFICIAL][ysl][10]",
  "description": "Redmi Y2/S2 Development ROMs, kernels, Recoveries",
  "__v": 0
},{
  "_id": {
    "$oid": "5fc4b49ce69740282c0a47c3"
  },
  "link": "/oxygenOs-ysl",
  "date": {
    "$date": "2020-11-30T09:00:12.235Z"
  },
  "heading": "OxygenOs[Endgame][4.0][port][10][Unofficial][ysl]",
  "description": "Redmi Y2/S2 Development ROMs, kernels, Recoveries",
  "__v": 0
},{
  "_id": {
    "$oid": "5fc4b5c6e69740282c0a47c4"
  },
  "link": "/rr-ysl",
  "date": {
    "$date": "2020-11-30T09:05:10.597Z"
  },
  "heading": "Ressurection Remix[8.6.2][Official][10][ysl]",
  "description": "Redmi Y2/S2 Development ROMs, kernels, Recoveries",
  "__v": 0
}]